Metadata-Version: 2.1
Name: pyparallelizer
Version: 1.0.0
Summary: A package that makes it easy to create Pypi packages
Home-page: UNKNOWN
Author: Isaac YIMGAING
Author-email: isaac.yimgaing@gmail.com
License: UNKNOWN
Keywords: PYTHON,DATAFRAME,MULTIPROCESSING
Platform: UNKNOWN
Classifier: Programming Language :: Python :: 3
Classifier: License :: OSI Approved :: MIT License
Classifier: Operating System :: OS Independent
